[
    {
        "group": "session",
        "privileges": ["get_session", "post_session"]
    },
    {
        "group":"backoffice",
        "privileges": [
            "post_user", "get_user", "delete_user", "put_user",
            "get_person", "post_person", "delete_person", "put_person",
            "post_role", "get_role", "delete_role", "put_role",
            "get_devices", "put_devices"
        ]
    },
    {
        "group":"backoffice_users",
        "privileges": [
            "post_user", "get_user", "put_user",
            "get_person", "post_person", "put_person",
            "get_role",
            "get_devices", "put_devices"
        ]
    },
    {
        "group": "files",
        "privileges": [
            "post_files", "get_files", "delete_files", "put_files",
            "get_files_s3", "post_files_s3", "delete_files_s3", "put_files_s3"
        ]
    },
    {
        "group":"notifications",
        "privileges":[
            "get_devices", "put_devices",
            "get_notifications", "put_notifications", "post_notifications", "delete_notifications"
        ]
    },
    {
        "group":"status",
        "privileges":[
            "get_status", "put_status", "post_status", "delete_status"
        ]
    },
    {
        "group":"teacher_actions",
        "privileges":[
            "get_period", "put_period", "post_period", "delete_period",
            "get_course", "put_course", "post_course", "delete_course",
            "get_group", "put_group", "post_group", "delete_group",
            "get_user_group", "put_user_group", "post_user_group", "delete_user_group",
            "get_mission_type", "put_mission_type", "post_mission_type", "delete_mission_type",
            "get_mission", "put_mission", "post_mission", "delete_mission",
            "get_mission_group", "put_mission_group", "post_mission_group", "delete_mission_group",
            "get_user_mission", "put_user_mission", "post_user_mission", "delete_user_mission"
            
        ]
    },
    {
        "group":"student_actions",
        "privileges":[
            "get_group", "get_user_group", "post_user_group", "get_mission_type", "get_mission", "get_mission_group",
            "get_user_mission"
        ]
    }
    

]
